imdbclassifier
