Metadata-Version: 1.0
Name: imdbclassifier
Version: 0.6.5
Summary: MLflow modules for binary classification in Keras
Home-page: http://github.com/dmatrix/jsd-mflow-examples/keras/imdbclassifier
Author: Jules S. Damji
Author-email: jules@databricks.com
License: None
Platform: UNKNOWN
